opsvis/__init__.py
opsvis/anim.py
opsvis/defo.py
opsvis/fibsec.py
opsvis/importing_modules.py
opsvis/model.py
opsvis/secforces.py
opsvis/settings.py
opsvis/stress.py
opsvis-1.3.4.dist-info/licenses/LICENSE
opsvis-1.3.4.dist-info/METADATA
opsvis-1.3.4.dist-info/WHEEL
opsvis-1.3.4.dist-info/top_level.txt
opsvis-1.3.4.dist-info/RECORD
