Metadata-Version: 2.4
Name: opsvis
Version: 1.3.4
Summary: OpenSeesPy (OpenSees) Python postprocessing and visualization module
Home-page: https://github.com/sewkokot/opsvis
Author: Seweryn Kokot
Author-email: sewkokot@gmail.com
Project-URL: Bug Tracker, https://github.com/sewkokot/opsvis/issues
Classifier: Programming Language :: Python :: 3
Classifier: License :: OSI Approved :: GNU General Public License v3 or later (GPLv3+)
Classifier: Operating System :: OS Independent
Requires-Python: >=3.6
License-File: LICENSE
Requires-Dist: openseespy
Dynamic: license-file
